nest_rpc_client/__init__.py
nest_rpc_client/client.py
nest_rpc_client/config/__init__.py
nest_rpc_client/config/nats.py
nest_rpc_client/config/rabbitmq.py
nest_rpc_client/config/redis.py
nest_rpc_client/config/tcp.py
nest_rpc_client/exceptions/rpc.py
nest_rpc_client/transport.py
nest_rpc_client/transports/__init__.py
nest_rpc_client/transports/mock.py
nest_rpc_client/transports/nats.py
nest_rpc_client/transports/rabbitmq.py
nest_rpc_client/transports/redis.py
nest_rpc_client/transports/tcp.py
nest_rpc_client/utils/__init__.py
nest_rpc_client/utils/parse_response.py
nest_rpc_client-1.3.3.dist-info/METADATA
nest_rpc_client-1.3.3.dist-info/WHEEL
nest_rpc_client-1.3.3.dist-info/RECORD
